cmem_client/__init__.py
cmem_client/auth_provider/__init__.py
cmem_client/auth_provider/abc.py
cmem_client/auth_provider/client_credentials.py
cmem_client/auth_provider/password.py
cmem_client/auth_provider/prefetched_token.py
cmem_client/client.py
cmem_client/components/__init__.py
cmem_client/components/graph_store.py
cmem_client/components/marketplace.py
cmem_client/components/sparql_wrapper.py
cmem_client/components/workspace.py
cmem_client/config.py
cmem_client/exceptions.py
cmem_client/logging_utils.py
cmem_client/models/__init__.py
cmem_client/models/access_condition.py
cmem_client/models/base.py
cmem_client/models/dataset.py
cmem_client/models/error.py
cmem_client/models/graph.py
cmem_client/models/item.py
cmem_client/models/logging_config.py
cmem_client/models/package.py
cmem_client/models/project.py
cmem_client/models/python_package.py
cmem_client/models/resource.py
cmem_client/models/token.py
cmem_client/models/url.py
cmem_client/models/workflow.py
cmem_client/repositories/__init__.py
cmem_client/repositories/access_conditions.py
cmem_client/repositories/base/__init__.py
cmem_client/repositories/base/abc.py
cmem_client/repositories/base/paged_list.py
cmem_client/repositories/base/plain_list.py
cmem_client/repositories/base/task_search.py
cmem_client/repositories/datasets.py
cmem_client/repositories/files.py
cmem_client/repositories/graph_imports.py
cmem_client/repositories/graphs.py
cmem_client/repositories/marketplace_packages.py
cmem_client/repositories/projects.py
cmem_client/repositories/protocols/__init__.py
cmem_client/repositories/protocols/create_item.py
cmem_client/repositories/protocols/delete_item.py
cmem_client/repositories/protocols/export_item.py
cmem_client/repositories/protocols/import_item.py
cmem_client/repositories/python_packages.py
cmem_client/repositories/workflows.py
cmem_client-0.7.1.dist-info/METADATA
cmem_client-0.7.1.dist-info/WHEEL
cmem_client-0.7.1.dist-info/licenses/LICENSE
cmem_client-0.7.1.dist-info/RECORD
