Metadata-Version: 2.4
Name: cmem-client
Version: 0.7.1
Summary: Next generation eccenca Corporate Memory client library.
License: Apache-2.0
License-File: LICENSE
Keywords: eccenca Corporate Memory,client
Author: eccenca GmbH
Author-email: cmempy-developer@eccenca.com
Requires-Python: >=3.13,<4
Classifier: Development Status :: 4 - Beta
Classifier: License :: OSI Approved :: Apache Software License
Classifier: Programming Language :: Python :: 3
Classifier: Programming Language :: Python :: 3.13
Classifier: Programming Language :: Python :: 3.14
Classifier: Topic :: Software Development :: Libraries :: Python Modules
Requires-Dist: eccenca-marketplace-client (>=0.7.0,<0.8.0)
Requires-Dist: httpx (>=0.27.0,<0.28.0)
Requires-Dist: pydantic (>=2.8.2,<3.0.0)
Requires-Dist: pyjwt (>=2.8.0,<3.0.0)
Requires-Dist: rdflib (>=7.2.1,<8.0.0)
Requires-Dist: xdg-base-dirs (>=6.0.2,<7.0.0)
